<workout_file>
    <uniqueId>1d28efbb-a7f6-4daa-a80f-c6453acd41c8</uniqueId>
    <legacyIdHash>4027067110</legacyIdHash>
    <name>Week 12.4 - Day 4</name>
    <description>Threshold Dev</description>
    <author>Marco Pinotti</author>
    <category>10-12wk FTP Builder</category>
    <WorkoutPlan>1</WorkoutPlan>
    <subcategory>Week 12</subcategory>
    <painIndex>1</painIndex>
    <authorIcon>UI/WhiteOrangeTheme/Workout_Select/brands/MarcoPinotti_Logo.tga</authorIcon>
    <sportType>bike</sportType>
    <workout>
        <Warmup Duration="600" PowerLow="0.5" PowerHigh="0.65" />
        <Ramp Duration="300" PowerLow="0.5" PowerHigh="1.0" />
        <SteadyState Duration="120" Power="0.65" />
        <SteadyState Duration="120" Power="0.81" />
        <SteadyState Duration="60" Power="0.95" />
        <SteadyState Duration="300" Power="0.5" />
        <IntervalsT Repeat="5" OnDuration="120" OnPower=".95" OffDuration="120" OffPower=".81" OverUnder="1" />
        <SteadyState Duration="600" Power="0.5" />
        <IntervalsT Repeat="5" OnDuration="120" OnPower=".95" OffDuration="120" OffPower=".81" OverUnder="1" />
        <Cooldown Duration="300" PowerHigh="0.65" PowerLow="0.5" />
    </workout>
</workout_file>